healthdes/ActivityBase.py
healthdes/Check.py
healthdes/DataCollection.py
healthdes/DecisionBase.py
healthdes/PersonBase.py
healthdes/ResourceBase.py
healthdes/Routing.py
healthdes/__init__.py
healthdes-0.0.2.dist-info/LICENSE
healthdes-0.0.2.dist-info/METADATA
healthdes-0.0.2.dist-info/WHEEL
healthdes-0.0.2.dist-info/top_level.txt
healthdes-0.0.2.dist-info/RECORD
