Metadata-Version: 2.1
Name: healthdes
Version: 0.0.2
Summary: A python library to support discrete event simulation in health and social care
Home-page: https://github.com/DiaAzul/healthdes
Author: David Plummer
Author-email: david.plummer@tanzo.org
License: BSD 3-Clause
Keywords: library simulation healthcare health care hospital
Platform: UNKNOWN
Classifier: Development Status :: 2 - Pre-Alpha
Classifier: Programming Language :: Python :: 3
Classifier: License :: OSI Approved :: BSD License
Classifier: Operating System :: OS Independent
Classifier: Intended Audience :: Healthcare Industry
Classifier: Topic :: Software Development :: Libraries
Requires-Python: >=3.7
Requires-Dist: simpy (>=4)
Requires-Dist: networkx (>=2)
Requires-Dist: pandas (>=1)
